<?xml version="1.0" encoding="utf-8"?>
<VisualState xmlns:xsi="http://www.w3.org/2001/XMLSchema-instance" xmlns:xsd="http://www.w3.org/2001/XMLSchema" ShowCheckBoxes="true">
  <TopNode>[0-1000]C:\Users\jaredpar\VsVim\VsVim\VsVim.csproj</TopNode>
  <SelectedNode>[0-1000]C:\Users\jaredpar\VsVim\VsVim\VsVim.csproj</SelectedNode>
  <ExcludeCategories>false</ExcludeCategories>
  <Nodes>
    <Node UniqueName="[0-1000]C:\Users\jaredpar\VsVim\VsVim\VsVim.csproj" Expanded="true" />
  </Nodes>
</VisualState>